cantera/yaml2ck.py
cantera/units.pxd
cantera/preconditioners.pxd
cantera/constants.pxd
cantera/__init__.pxd
cantera/mixture.pxd
cantera/kinetics.pxd
cantera/onedim.py
cantera/transport.pxd
cantera/ck2yaml.py
cantera/ctcxx.pxd
cantera/__init__.py
cantera/solutionbase.pxd
cantera/yamlwriter.pxd
cantera/reactionpath.pxd
cantera/_cantera.cpython-310-darwin.so
cantera/thermo.pxd
cantera/liquidvapor.py
cantera/utils.py
cantera/speciesthermo.pxd
cantera/func1.pxd
cantera/composite.py
cantera/reactor.pxd
cantera/interrupts.py
cantera/ctml2yaml.py
cantera/reaction.pxd
cantera/cti2yaml.py
cantera/_onedim.pxd
cantera/delegator.pxd
cantera/data.py
cantera/_utils.pxd
cantera/test/README.txt
cantera/with_units/solution.py
cantera/with_units/__init__.py
cantera/examples/README.txt
cantera/data/ohn.yaml
cantera/data/nDodecane_Reitz.yaml
cantera/data/graphite.yaml
cantera/data/h2o2.yaml
cantera/data/water.yaml
cantera/data/YZA.yaml
cantera/data/KOH.yaml
cantera/data/SiF4_NH3_mec.yaml
cantera/data/nasa_gas.yaml
cantera/data/gri30.yaml
cantera/data/methane_pox_on_pt.yaml
cantera/data/silicon_carbide.yaml
cantera/data/nasa_condensed.yaml
cantera/data/silicon.yaml
cantera/data/airNASA9.yaml
cantera/data/liquidvapor.yaml
cantera/data/critical-properties.yaml
cantera/data/sofc.yaml
cantera/data/diamond.yaml
cantera/data/lithium_ion_battery.yaml
cantera/data/air.yaml
cantera/data/element-standard-entropies.yaml
cantera/data/gri30_ion.yaml
cantera/data/covdepsurf.yaml
cantera/data/ptcombust.yaml
cantera/data/gri30_highT.yaml
Cantera-3.0.1.dist-info/RECORD
Cantera-3.0.1.dist-info/WHEEL
Cantera-3.0.1.dist-info/entry_points.txt
Cantera-3.0.1.dist-info/top_level.txt
Cantera-3.0.1.dist-info/LICENSE.txt
Cantera-3.0.1.dist-info/METADATA
