Metadata-Version: 2.1
Name: Cantera
Version: 3.0.1
Summary: Cantera is an open-source suite of tools for problems involving chemical kinetics, thermodynamics, and transport processes.
Home-page: https://cantera.org
Author: Cantera Developers
Author-email: developers@cantera.org
License: BSD 3-Clause License
Project-URL: Documentation, https://cantera.org/documentation
Project-URL: Funding, https://numfocus.org/donate-to-cantera
Project-URL: Source, https://github.com/Cantera/cantera
Project-URL: Tracker, https://github.com/Cantera/cantera/issues
Keywords: chemistry physics
Classifier: Development Status :: 5 - Production/Stable
Classifier: Intended Audience :: Education
Classifier: Intended Audience :: Science/Research
Classifier: License :: OSI Approved :: BSD License
Classifier: Operating System :: MacOS :: MacOS X
Classifier: Operating System :: Microsoft :: Windows
Classifier: Operating System :: POSIX :: Linux
Classifier: Programming Language :: C
Classifier: Programming Language :: C++
Classifier: Programming Language :: Cython
Classifier: Programming Language :: Fortran
Classifier: Programming Language :: Python :: 3 :: Only
Classifier: Programming Language :: Python :: 3.8
Classifier: Programming Language :: Python :: 3.9
Classifier: Programming Language :: Python :: 3.10
Classifier: Programming Language :: Python :: 3.11
Classifier: Programming Language :: Python :: 3.12
Classifier: Programming Language :: Python :: 3.13
Classifier: Programming Language :: Python :: Implementation :: CPython
Classifier: Topic :: Scientific/Engineering :: Chemistry
Classifier: Topic :: Scientific/Engineering :: Physics
License-File: LICENSE.txt
Requires-Dist: numpy <3,>=1.12.0
Requires-Dist: ruamel.yaml >=0.15.34
Provides-Extra: pandas
Requires-Dist: pandas ; extra == 'pandas'
Provides-Extra: units
Requires-Dist: pint ; extra == 'units'
Requires-Dist: numpy <2.0 ; (python_version <= "3.9") and extra == 'units'
